MANIFEST.in
README.txt
bootstrap.py
buildout.cfg
setup.cfg
setup.py
blockdiagcontrib/__init__.py
blockdiagcontrib/cisco.py
blockdiagcontrib/images/cisco/100baset hub.jpg
blockdiagcontrib/images/cisco/10700.jpg
blockdiagcontrib/images/cisco/10GE_FCoE.jpg
blockdiagcontrib/images/cisco/15200.jpg
blockdiagcontrib/images/cisco/3174 (desktop).jpg
blockdiagcontrib/images/cisco/3200 mobile access router.jpg
blockdiagcontrib/images/cisco/3x74 (floor).jpg
blockdiagcontrib/images/cisco/6700 series.jpg
blockdiagcontrib/images/cisco/7500ars (7513).jpg
blockdiagcontrib/images/cisco/ACS.jpg
blockdiagcontrib/images/cisco/ASR 1000 Series.jpg
blockdiagcontrib/images/cisco/AXP.jpg
blockdiagcontrib/images/cisco/CUBE.jpg
blockdiagcontrib/images/cisco/Ground terminal.jpg
blockdiagcontrib/images/cisco/MSE.jpg
blockdiagcontrib/images/cisco/MXE.jpg
blockdiagcontrib/images/cisco/Mediator.jpg
blockdiagcontrib/images/cisco/NCE router.jpg
blockdiagcontrib/images/cisco/NCE.jpg
blockdiagcontrib/images/cisco/Nexus 1000.jpg
blockdiagcontrib/images/cisco/Nexus 2000.jpg
blockdiagcontrib/images/cisco/Nexus 5000.jpg
blockdiagcontrib/images/cisco/Nexus 7000.jpg
blockdiagcontrib/images/cisco/RF modem.jpg
blockdiagcontrib/images/cisco/Service Module.jpg
blockdiagcontrib/images/cisco/Service router.jpg
blockdiagcontrib/images/cisco/Services.jpg
blockdiagcontrib/images/cisco/Set top box.jpg
blockdiagcontrib/images/cisco/Space router.jpg
blockdiagcontrib/images/cisco/TP MCU.jpg
blockdiagcontrib/images/cisco/VSD.jpg
blockdiagcontrib/images/cisco/VSS.jpg
blockdiagcontrib/images/cisco/access gateway.jpg
blockdiagcontrib/images/cisco/accesspoint.jpg
blockdiagcontrib/images/cisco/ace.jpg
blockdiagcontrib/images/cisco/adm.jpg
blockdiagcontrib/images/cisco/androgenous person.jpg
blockdiagcontrib/images/cisco/antenna.jpg
blockdiagcontrib/images/cisco/asic processor.jpg
blockdiagcontrib/images/cisco/ata.jpg
blockdiagcontrib/images/cisco/atm 3800.jpg
blockdiagcontrib/images/cisco/atm fast gigabit etherswitch.jpg
blockdiagcontrib_cisco.egg-info/PKG-INFO
blockdiagcontrib_cisco.egg-info/SOURCES.txt
blockdiagcontrib_cisco.egg-info/dependency_links.txt
blockdiagcontrib_cisco.egg-info/entry_points.txt
blockdiagcontrib_cisco.egg-info/namespace_packages.txt
blockdiagcontrib_cisco.egg-info/requires.txt
blockdiagcontrib_cisco.egg-info/top_level.txt